{
  "id": 20030457,
  "updated": "2019-02-18T19:03:06Z",
  "additionalIndexing": "2841",
  "affairType": {
    "abbreviation": "Iv. pa.",
    "id": 4,
    "name": "Initiative parlementaire"
  },
  "author": {
    "councillor": {
      "code": 2502,
      "gender": "m",
      "id": 478,
      "name": "Joder Rudolf",
      "officialDenomination": "Joder"
    },
    "faction": {
      "abbreviation": "Groupe V",
      "id": 4,
      "name": "Groupe de l'Union démocratique du Centre"
    },
    "type": "author"
  },
  "deposit": {
    "council": {
      "abbreviation": "CN",
      "id": 1,
      "name": "Conseil national",
      "type": "N"
    },
    "date": "2003-10-03T00:00:00Z",
    "legislativePeriod": 46,
    "session": "4620"
  },
  "descriptors": [
    {
      "key": "L06K010505110101",
      "name": "Krankenpflege",
      "type": 1
    },
    {
      "key": "L04K01050401",
      "name": "arztähnlicher Beruf",
      "type": 1
    },
    {
      "key": "L04K01050507",
      "name": "Gesundheitsförderung",
      "type": 1
    },
    {
      "key": "L06K070305020401",
      "name": "Qualitätssicherung",
      "type": 1
    },
    {
      "key": "L04K13020308",
      "name": "Unterricht für arztähnliche Berufe",
      "type": 1
    },
    {
      "key": "L05K0105051101",
      "name": "Spital",
      "type": 2
    },
    {
      "key": "L04K13020306",
      "name": "medizinischer Unterricht",
      "type": 2
    }
  ],
  "drafts": [
    {
      "consultation": {
        "resolutions": [
          {
            "category": {
              "id": 5,
              "name": "Adm"
            },
            "council": {
              "abbreviation": "CN",
              "id": 1,
              "name": "Conseil national",
              "type": "N"
            },
            "date": "2004-08-30T00:00:00Z",
            "text": "Retrait",
            "type": 17
          }
        ]
      },
      "federalCouncilProposal": {
      },
      "index": 0,
      "links": [

      ],
      "preConsultations": [
        {
          "committee": {
            "abbreviation": "CSSS-CN",
            "id": 6,
            "name": "Commission de la sécurité sociale et de la santé publique CN",
            "abbreviation1": "CSSS-CN",
            "abbreviation2": "CSSS",
            "committeeNumber": 6,
            "council": {
              "abbreviation": "CN",
              "id": 1,
              "name": "Conseil national",
              "type": "N"
            },
            "typeCode": 1
          },
          "date": "2003-10-03T00:00:00Z",
          "registrations": [

          ]
        }
      ],
      "references": [

      ],
      "relatedDepartments": [

      ],
      "states": [
        {
          "date": "/Date(1065132000000+0200)/",
          "id": 24,
          "name": "Non encore traité au conseil"
        },
        {
          "date": "/Date(1093816800000+0200)/",
          "id": 27,
          "name": "Liquidé"
        }
      ],
      "texts": [

      ]
    }
  ],
  "handling": {
    "date": "2004-08-30T00:00:00Z",
    "legislativePeriod": 47,
    "session": "4705"
  },
  "language": "fr",
  "priorityCouncils": [
    {
      "abbreviation": "CN",
      "id": 1,
      "name": "Conseil national",
      "type": "N",
      "priority": 1
    }
  ],
  "relatedAffairs": [

  ],
  "roles": [
    {
      "councillor": {
        "code": 2502,
        "gender": "m",
        "id": 478,
        "name": "Joder Rudolf",
        "officialDenomination": "Joder"
      },
      "faction": {
        "abbreviation": "Groupe V",
        "id": 4,
        "name": "Groupe de l'Union démocratique du Centre"
      },
      "type": "author"
    }
  ],
  "sequentialNumber": 204,
  "shortId": "03.457",
  "state": {
    "id": 27,
    "name": "Liquidé",
    "doneKey": "1",
    "newKey": 0
  },
  "texts": [
    {
      "type": {
        "id": 6,
        "name": "Développement"
      },
      "value": "<p>Depuis quelques temps déjà, de multiples problèmes touchent le domaine des soins infirmiers et des professions médicales. Ces problèmes se répercutent sur les soins prodigués aux patients et sur les conditions de travail du personnel soignant. Compte tenu de l'importance que représentent les soins infirmiers pour la population, des mesures doivent être prises au plus vite.</p>"
    },
    {
      "type": {
        "id": 5,
        "name": "Texte déposé"
      },
      "value": "<p>Conformément à l'article 160 alinéa 1er de la constitution et à l'article 21bis de la loi sur les rapports entre les conseils, je présente une initiative parlementaire conçue en termes généraux: </p><p>Il faut élaborer un projet de loi comprenant: </p><p>1. la revalorisation générale des soins infirmiers et le renforcement du statut juridique du personnel soignant;</p><p>2. la définition et le but de ces soins, conçus comme des prestations fournies aux malades pour qu'ils recouvrent la santé, mais aussi pour qu'ils la conservent, voire améliorent leur état de santé;</p><p>3. l'obligation, pour les hôpitaux et institutions du même genre, d'apporter la preuve qu'ils fournissent des soins de qualité et en quantité suffisante.</p>"
    },
    {
      "type": {
        "id": 1,
        "name": "Titre de l'objet"
      },
      "value": "Revaloriser les professions paramédicales"
    }
  ],
  "title": "Revaloriser les professions paramédicales"
}