{
  "id": 20045064,
  "updated": "2019-02-18T19:03:06Z",
  "additionalIndexing": "34",
  "affairType": {
    "abbreviation": "Fra.",
    "id": 14,
    "name": "Fragestunde. Frage"
  },
  "author": {
    "councillor": {
      "code": 2333,
      "gender": "m",
      "id": 241,
      "name": "Zisyadis Josef",
      "officialDenomination": "Zisyadis"
    },
    "faction": {
      "abbreviation": "Fraktionslos",
      "code": "-",
      "id": 99,
      "name": "Fraktionslos"
    },
    "type": "author"
  },
  "deposit": {
    "council": {
      "abbreviation": "NR",
      "id": 1,
      "name": "Nationalrat",
      "type": "N"
    },
    "date": "2004-03-03T00:00:00Z",
    "legislativePeriod": 47,
    "session": "4702"
  },
  "descriptors": [
    {
      "key": "L05K1202050101",
      "name": "Fernsehen",
      "type": 1
    },
    {
      "key": "L05K1202050110",
      "name": "Sendekonzession",
      "type": 1
    },
    {
      "key": "L05K1202040104",
      "name": "Telekommunikationstarif",
      "type": 1
    }
  ],
  "drafts": [
    {
      "consultation": {
        "resolutions": [

        ]
      },
      "federalCouncilProposal": {
      },
      "index": 0,
      "links": [

      ],
      "preConsultations": [

      ],
      "references": [

      ],
      "relatedDepartments": [
        {
          "abbreviation": "UVEK",
          "id": 9,
          "name": "Departement für Umwelt, Verkehr, Energie und Kommunikation",
          "leading": true
        }
      ],
      "states": [
        {
          "date": "/Date(1078268400000+0100)/",
          "id": 27,
          "name": "Erledigt"
        }
      ],
      "texts": [

      ]
    }
  ],
  "handling": {
    "date": "2004-03-03T00:00:00Z",
    "legislativePeriod": 47,
    "session": "4702"
  },
  "language": "de",
  "priorityCouncils": [
    {
      "abbreviation": "NR",
      "id": 1,
      "name": "Nationalrat",
      "type": "N",
      "priority": 1
    }
  ],
  "relatedAffairs": [

  ],
  "roles": [
    {
      "councillor": {
        "code": 2333,
        "gender": "m",
        "id": 241,
        "name": "Zisyadis Josef",
        "officialDenomination": "Zisyadis"
      },
      "faction": {
        "abbreviation": "Fraktionslos",
        "code": "-",
        "id": 99,
        "name": "Fraktionslos"
      },
      "type": "author"
    }
  ],
  "shortId": "04.5064",
  "state": {
    "id": 27,
    "name": "Erledigt",
    "doneKey": "1",
    "newKey": 0
  },
  "texts": [
    {
      "type": {
        "id": 14,
        "name": "Antwort BR / Büro"
      },
      "value": "<p>Viele europäische Fernsehstationen bauen heute das so genannte TeleVoting in bestimmte Sendeformate ein, weil sie damit Einnahmen erzielen und daraus die betreffende Sendung mitfinanzieren können. Das ist heutige Medienrealität.</p><p>Die SRG hat in den letzten Wochen auch TeleVoting in der Sendung \"MusicStar\" praktiziert. Es ist unbestritten, dass sie damit Einnahmen erzielen konnte, die aber nach Angaben der SRG wiederum ins Programm fliessen sollen.</p><p>So wie die SRG das TeleVoting bis heute gehandhabt hat, ist darin keine Verletzung des Radio- und Fernsehgesetzes oder der Konzession zu sehen.</p><p>Wichtig ist aber, dass den Zuschauerinnen und Zuschauern die Kosten dieser gebührenpflichtigen Telefonnummern und der SMS bekannt sind und die Preisbekanntgabeverordnung eingehalten wird.</p>"
    },
    {
      "type": {
        "id": 5,
        "name": "Eingereichter Text"
      },
      "value": "<p>In Fernsehsendungen werden die Zuschauer immer wieder dazu aufgefordert, mit Telefonanrufen oder kostenpflichtigen SMS an Abstimmungen teilzunehmen.</p><p>Kann der Bundesrat uns sagen, ob dieser Finanzierungsmodus mit der Konzession vereinbar ist?</p>"
    },
    {
      "type": {
        "id": 1,
        "name": "Titel des Geschäftes"
      },
      "value": "SMS-Taxierung"
    }
  ],
  "title": "SMS-Taxierung"
}