{
  "id": 20103533,
  "updated": "2019-02-18T19:03:06Z",
  "additionalIndexing": "52;55;66",
  "affairType": {
    "abbreviation": "Po.",
    "id": 6,
    "name": "Postulat"
  },
  "author": {
    "councillor": {
      "code": 2541,
      "gender": "m",
      "id": 519,
      "name": "Walter Hansjörg",
      "officialDenomination": "Walter"
    },
    "faction": {
      "abbreviation": "Groupe V",
      "id": 4,
      "name": "Groupe de l'Union démocratique du Centre"
    },
    "type": "author"
  },
  "deposit": {
    "council": {
      "abbreviation": "CN",
      "id": 1,
      "name": "Conseil national",
      "type": "N"
    },
    "date": "2010-06-17T00:00:00Z",
    "legislativePeriod": 48,
    "session": "4814"
  },
  "descriptors": [
    {
      "key": "L05K0102040703",
      "name": "Wasserversorgung",
      "type": 1
    },
    {
      "key": "L04K06030409",
      "name": "Wasserreserven",
      "type": 1
    },
    {
      "key": "L05K0705030107",
      "name": "Wasserwirtschaft",
      "type": 1
    },
    {
      "key": "L05K0701030902",
      "name": "Mangel",
      "type": 1
    },
    {
      "key": "L06K140102030701",
      "name": "landwirtschaftliches Wasserbauvorhaben",
      "type": 1
    },
    {
      "key": "L04K06010504",
      "name": "Wassernutzung",
      "type": 2
    },
    {
      "key": "L04K06030302",
      "name": "Wasser",
      "type": 2
    },
    {
      "key": "L04K06010407",
      "name": "Gewässerschutz",
      "type": 2
    },
    {
      "key": "L04K06030110",
      "name": "Wasserlauf",
      "type": 2
    },
    {
      "key": "L04K06010412",
      "name": "Schutzgebiet",
      "type": 2
    },
    {
      "key": "L06K080203070101",
      "name": "Güterabwägung",
      "type": 2
    }
  ],
  "drafts": [
    {
      "consultation": {
        "resolutions": [
          {
            "category": {
              "id": 3,
              "name": "Normal"
            },
            "council": {
              "abbreviation": "CN",
              "id": 1,
              "name": "Conseil national",
              "type": "N"
            },
            "date": "2010-10-01T00:00:00Z",
            "text": "Adoption",
            "type": 20
          },
          {
            "category": {
              "id": 3,
              "name": "Normal"
            },
            "council": {
              "abbreviation": "CN",
              "id": 1,
              "name": "Conseil national",
              "type": "N"
            },
            "date": "2013-06-12T00:00:00Z",
            "text": "Classement",
            "type": 15
          },
          {
            "category": {
              "id": 4,
              "name": "Complément"
            },
            "council": {
              "abbreviation": "CN",
              "id": 1,
              "name": "Conseil national",
              "type": "N"
            },
            "date": "2013-06-12T00:00:00Z",
            "text": "(dans le cadre de l’examen de l’objet 13.006)",
            "type": 0
          }
        ]
      },
      "federalCouncilProposal": {
        "code": "+",
        "date": "2010-09-01T00:00:00Z",
        "text": "Le Conseil fédéral propose d'accepter le postulat."
      },
      "index": 0,
      "links": [

      ],
      "preConsultations": [

      ],
      "references": [

      ],
      "relatedDepartments": [
        {
          "abbreviation": "DETEC",
          "id": 9,
          "name": "Département  de l'environnement, des transports, de l'énergie et de la communication",
          "leading": true
        }
      ],
      "states": [
        {
          "date": "/Date(1276725600000+0200)/",
          "id": 24,
          "name": "Non encore traité au conseil"
        },
        {
          "date": "/Date(1285884000000+0200)/",
          "id": 26,
          "name": "Adopté"
        },
        {
          "date": "/Date(1378159200000+0200)/",
          "id": 25,
          "name": "Classé"
        }
      ],
      "texts": [

      ]
    }
  ],
  "handling": {
    "date": "2010-10-01T00:00:00Z",
    "legislativePeriod": 48,
    "session": "4815"
  },
  "language": "fr",
  "priorityCouncils": [
    {
      "abbreviation": "CN",
      "id": 1,
      "name": "Conseil national",
      "type": "N",
      "priority": 1
    }
  ],
  "relatedAffairs": [

  ],
  "roles": [
    {
      "councillor": {
        "code": 2670,
        "gender": "m",
        "id": 3867,
        "name": "Aebi Andreas",
        "officialDenomination": "Aebi Andreas"
      },
      "type": "cosign"
    },
    {
      "councillor": {
        "code": 2656,
        "gender": "m",
        "id": 1336,
        "name": "Zemp Markus",
        "officialDenomination": "Zemp"
      },
      "type": "cosign"
    },
    {
      "councillor": {
        "code": 2588,
        "gender": "m",
        "id": 1104,
        "name": "Büchler Jakob",
        "officialDenomination": "Büchler Jakob"
      },
      "type": "cosign"
    },
    {
      "councillor": {
        "code": 2745,
        "gender": "m",
        "id": 4032,
        "name": "Jans Beat",
        "officialDenomination": "Jans"
      },
      "type": "cosign"
    },
    {
      "councillor": {
        "code": 2354,
        "gender": "f",
        "id": 273,
        "name": "Gadient Brigitta M.",
        "officialDenomination": "Gadient"
      },
      "type": "cosign"
    },
    {
      "councillor": {
        "code": 2592,
        "gender": "m",
        "id": 1133,
        "name": "Darbellay Christophe",
        "officialDenomination": "Darbellay"
      },
      "type": "cosign"
    },
    {
      "councillor": {
        "code": 2600,
        "gender": "f",
        "id": 1106,
        "name": "Häberli-Koller Brigitte",
        "officialDenomination": "Häberli-Koller"
      },
      "type": "cosign"
    },
    {
      "councillor": {
        "code": 2713,
        "gender": "m",
        "id": 3910,
        "name": "von Siebenthal Erich",
        "officialDenomination": "von Siebenthal"
      },
      "type": "cosign"
    },
    {
      "councillor": {
        "code": 2569,
        "gender": "f",
        "id": 806,
        "name": "Graf Maya",
        "officialDenomination": "Graf Maya"
      },
      "type": "cosign"
    },
    {
      "councillor": {
        "code": 2737,
        "gender": "m",
        "id": 4014,
        "name": "Brönnimann Andreas",
        "officialDenomination": "Brönnimann"
      },
      "type": "cosign"
    },
    {
      "councillor": {
        "code": 2696,
        "gender": "f",
        "id": 3893,
        "name": "Lachenmeier-Thüring Anita",
        "officialDenomination": "Lachenmeier"
      },
      "type": "cosign"
    },
    {
      "councillor": {
        "code": 2448,
        "gender": "f",
        "id": 395,
        "name": "Fässler-Osterwalder Hildegard",
        "officialDenomination": "Fässler Hildegard"
      },
      "type": "cosign"
    },
    {
      "councillor": {
        "code": 2497,
        "gender": "m",
        "id": 473,
        "name": "Hassler Hansjörg",
        "officialDenomination": "Hassler"
      },
      "type": "cosign"
    },
    {
      "councillor": {
        "code": 2675,
        "gender": "m",
        "id": 3872,
        "name": "Bourgeois Jacques",
        "officialDenomination": "Bourgeois"
      },
      "type": "cosign"
    },
    {
      "councillor": {
        "code": 2541,
        "gender": "m",
        "id": 519,
        "name": "Walter Hansjörg",
        "officialDenomination": "Walter"
      },
      "faction": {
        "abbreviation": "Groupe V",
        "id": 4,
        "name": "Groupe de l'Union démocratique du Centre"
      },
      "type": "author"
    }
  ],
  "shortId": "10.3533",
  "state": {
    "id": 25,
    "name": "Classé",
    "doneKey": "0",
    "newKey": 0
  },
  "texts": [
    {
      "type": {
        "id": 6,
        "name": "Développement"
      },
      "value": "<p>La Suisse passe pour être le château d'eau de l'Europe. Mais cela ne nous dispense pas de gérer nos ressources en eau en toute connaissance de cause, dans le respect du développement durable. Des étés secs comme celui de 2003 ou des situations difficiles comme en 2009 montrent que nous pouvons nous aussi être victimes d'une pénurie d'eau et que des questions ayant trait à la répartition des ressources disponibles peuvent se poser. Les modèles actuels d'évolution du climat prévoient l'augmentation du nombre de périodes où l'accès à l'eau sera limité. Les conflits éclatent quand il faut déterminer, en cas de pénurie, s'il faut réserver l'eau à la production d'électricité, à la production de denrées alimentaires (irrigation) ou à l'industrie (systèmes de refroidissement). Mais ils éclatent aussi quand il s'agit d'effectuer un captage d'eau potable dans une zone naturelle protégée ou de construire un barrage sur un cours d'eau pour produire de l'électricité. La stratégie de l'eau indiquera la manière de gérer ce genre de conflits, mais aussi quel groupe d'utilisateurs pourra consommer de l'eau, à quel moment et en quelles quantités. Elle indiquera en outre les endroits où les utilisations judicieuses et modérées sont possibles et où la protection est prioritaire. Pour cela, la stratégie devra être élaborée dans le cadre d'un processus participatif englobant toutes les organisations et tous les acteurs concernés.</p>"
    },
    {
      "type": {
        "id": 14,
        "name": "Réponse CF / Bureau"
      },
      "value": "<p>L'économie hydraulique en Suisse est en pleine évolution. Les principales réflexions concernent la gestion des eaux par bassin versant tout comme les options pour la préparation institutionnelle et organisationnelle des défis futurs. </p><p>Ces thématiques sont abordées par le programme national de recherche PNR 61 \"Gestion durable de l'eau\" (2010-2014), qui se penche en particulier sur les questions liées aux changements climatiques, aux données hydrologiques et à la gestion de l'eau. La stratégie nationale d'adaptation aux changements climatiques - pour laquelle le Conseil fédéral a mandaté en août 2009 le DETEC et d'autres départements concernés - porte également sur la gestion des eaux. Elle sera soumise pour approbation au Conseil fédéral fin 2011. Cependant, une stratégie de gestion des eaux va au-delà de l'adaptation aux changements climatiques. En effet, d'autres acteurs et d'autres intérêts entrent en ligne de compte qui accentuent les pressions sur les ressources en eau, d'où le besoin de nouveaux principes.</p><p>Le Conseil fédéral approuve donc l'élaboration d'une stratégie concrète de gestion des eaux, comprenant une base légale qui respecte la répartition des tâches entre la Confédération, les cantons, les communes et les particuliers. Cette stratégie doit comprendre les principaux modes d'exploitation (p. ex. approvisionnement en eau, énergie hydraulique, irrigation), la protection des eaux (qualité des eaux, écoulement, aménagement de l'espace vital) et celle contre les crues.</p>"
    },
    {
      "type": {
        "id": 5,
        "name": "Texte déposé"
      },
      "value": "<p>Le Conseil fédéral est chargé d'élaborer un rapport qui présentera une stratégie de l'eau reposant sur le développement durable et tenant compte des besoins des différents groupes d'utilisateurs. Cette stratégie fournira des ébauches de mesures et de solutions tant pour surmonter des événements à court terme, par exemple une pénurie d'eau passagère à l'échelon local, que pour relever des défis à long terme, par exemple la manière dont le Conseil fédéral entend réagir à la raréfaction générale des ressources en eau, notamment en raison du changement climatique. La stratégie donnera à cet égard une vue d'ensemble de cette constellation de sujets et établira des directives, des ébauches de mesures et des règles du jeu concernant les points suivants:</p><p>- réglementation de l'accès à l'eau et répartition de l'eau destinée aux ménages, à l'agriculture, à la production d'énergie et à l'industrie, mais aussi à l'intérieur des groupes d'utilisateurs, en rapport avec la raréfaction de l'eau à court et à moyen termes;</p><p>- définition de règles du jeu pour ménager les intérêts des protecteurs des ressources en eau et ceux des utilisateurs (p. ex. pesée des intérêts dans les cas où la construction d'un ouvrage de production d'énergie hydraulique est projetée dans une zone naturelle protégée);</p><p>- élaboration d'une base juridique pour mettre en oeuvre une stratégie de l'eau en tenant compte de la répartition des tâches entre la Confédération, les cantons, les communes et les particuliers.</p>"
    },
    {
      "type": {
        "id": 1,
        "name": "Titre de l'objet"
      },
      "value": "Eau et agriculture. Les défis de demain"
    }
  ],
  "title": "Eau et agriculture. Les défis de demain"
}