{
  "id": 20060453,
  "updated": "2019-02-18T19:03:06Z",
  "additionalIndexing": "2841",
  "affairType": {
    "abbreviation": "Iv. pa.",
    "id": 4,
    "name": "Iniziativa parlamentare"
  },
  "author": {
    "councillor": {
      "code": 2380,
      "gender": "f",
      "id": 316,
      "name": "Egerszegi-Obrist Christine",
      "officialDenomination": "Egerszegi-Obrist"
    },
    "faction": {
      "abbreviation": "Gruppo RL",
      "id": 1,
      "name": "Gruppo liberale-radicale"
    },
    "type": "author"
  },
  "deposit": {
    "council": {
      "abbreviation": "CN",
      "id": 1,
      "name": "Consiglio nazionale",
      "type": "N"
    },
    "date": "2006-06-23T00:00:00Z",
    "legislativePeriod": 47,
    "session": "4713"
  },
  "descriptors": [
    {
      "key": "L05K0101030401",
      "name": "Euthanasie",
      "type": 1
    },
    {
      "key": "L05K0503010102",
      "name": "Gesetz",
      "type": 1
    },
    {
      "key": "L04K08020313",
      "name": "Kontrolle",
      "type": 1
    },
    {
      "key": "L05K0101030204",
      "name": "Vereinigung",
      "type": 1
    },
    {
      "key": "L04K01010206",
      "name": "Freitod",
      "type": 1
    },
    {
      "key": "L04K01050213",
      "name": "Palliativmedizin",
      "type": 2
    }
  ],
  "drafts": [
    {
      "consultation": {
        "resolutions": [
          {
            "category": {
              "id": 3,
              "name": "Normale"
            },
            "council": {
              "abbreviation": "CN",
              "id": 1,
              "name": "Consiglio nazionale",
              "type": "N"
            },
            "date": "2012-09-26T00:00:00Z",
            "text": "Non è dato seguito",
            "type": 51
          }
        ]
      },
      "federalCouncilProposal": {
      },
      "index": 0,
      "links": [

      ],
      "preConsultations": [
        {
          "committee": {
            "abbreviation": "CAG-CN",
            "id": 12,
            "name": "Commissione degli affari giuridici CN",
            "abbreviation1": "CAG-CN",
            "abbreviation2": "CAG",
            "committeeNumber": 12,
            "council": {
              "abbreviation": "CN",
              "id": 1,
              "name": "Consiglio nazionale",
              "type": "N"
            },
            "typeCode": 1
          },
          "date": "2006-06-23T00:00:00Z",
          "registrations": [
            {
              "correspondents": [
                {
                  "council": {
                    "abbreviation": "CN",
                    "id": 1,
                    "name": "Consiglio nazionale",
                    "type": "N"
                  },
                  "councillor": {
                    "code": 2711,
                    "gender": "m",
                    "id": 3908,
                    "name": "von Graffenried Alec",
                    "officialDenomination": "von Graffenried"
                  },
                  "language": "de"
                },
                {
                  "council": {
                    "abbreviation": "CN",
                    "id": 1,
                    "name": "Consiglio nazionale",
                    "type": "N"
                  },
                  "councillor": {
                    "code": 3604,
                    "gender": "f",
                    "id": 4108,
                    "name": "Chevalley Isabelle",
                    "officialDenomination": "Chevalley"
                  },
                  "language": "fr"
                }
              ],
              "sessionId": "4904"
            }
          ],
          "treatmentCategory": "IIIb"
        }
      ],
      "references": [

      ],
      "relatedDepartments": [

      ],
      "states": [
        {
          "date": "/Date(1151013600000+0200)/",
          "id": 24,
          "name": "Non ancora trattato dalla Camera"
        },
        {
          "date": "/Date(1348610400000+0200)/",
          "id": 27,
          "name": "Liquidato"
        }
      ],
      "texts": [

      ]
    }
  ],
  "handling": {
    "date": "2012-09-26T00:00:00Z",
    "legislativePeriod": 49,
    "session": "4905"
  },
  "language": "it",
  "priorityCouncils": [
    {
      "abbreviation": "CN",
      "id": 1,
      "name": "Consiglio nazionale",
      "type": "N",
      "priority": 1
    }
  ],
  "relatedAffairs": [

  ],
  "roles": [
    {
      "councillor": {
        "code": 2614,
        "gender": "f",
        "id": 1139,
        "name": "Markwalder Christa",
        "officialDenomination": "Markwalder"
      },
      "type": "cosign"
    },
    {
      "councillor": {
        "code": 2565,
        "gender": "m",
        "id": 801,
        "name": "Abate Fabio",
        "officialDenomination": "Abate"
      },
      "type": "cosign"
    },
    {
      "councillor": {
        "code": 2380,
        "gender": "f",
        "id": 316,
        "name": "Egerszegi-Obrist Christine",
        "officialDenomination": "Egerszegi-Obrist"
      },
      "faction": {
        "abbreviation": "Gruppo RL",
        "id": 1,
        "name": "Gruppo liberale-radicale"
      },
      "type": "author"
    }
  ],
  "sequentialNumber": 257,
  "shortId": "06.453",
  "state": {
    "id": 27,
    "name": "Liquidato",
    "doneKey": "1",
    "newKey": 0
  },
  "texts": [
    {
      "type": {
        "id": 6,
        "name": "Motivazione"
      },
      "value": "<p>Già nel marzo 2004 una mozione (03.3180) approvata dalle Camere federali invitava il Consiglio federale a proporre norme legali concernenti l'eutanasia e misure per la promozione della medicina palliativa. Un'analoga mozione (05.3352) inoltrata nel giugno 2005 dal gruppo radicale-democratico metteva l'accento sulla necessità di eliminare la zona d'ombra nel disciplinamento delle condizioni e modalità alle quali è permesso porre fine alla propria vita.</p><p>Non è dunque comprensibile che il Consiglio federale esiti a formulare un testo di legge sull'eutanasia che avvii nell'organo legislativo un dibattito su una questione sociale e politica così importante, tanto più che invece l'inizio di ogni nuova vita è stato disciplinato a livello federale fin nei minimi particolari. </p><p>Un testo di questo genere deve tener chiaramente conto della libertà decisionale e dell'autodeterminazione di ciascuno dalla nascita alla morte, senza tuttavia sfociare in un disciplinamento eccessivo.</p><p>Oltre all'elaborazione di direttive legali sull'eutanasia indiretta attiva e passiva che non riguardano solo la decisione di porre fine alla propria vita, ma anche le decisioni delle persone coinvolte (parenti, medici, personale curante), sono necessarie misure per migliorare la situazione della medicina palliativa.</p><p>Inoltre bisogna disciplinare la sorveglianza ed il controllo delle organizzazioni che assistono chi decide di suicidarsi. Non solo al fine di evitare che persone dall'estero vengano appositamente in Svizzera per porre fine ai loro giorni, ma anche perché le persone interessate possano sentirsi sicure di non scivolare nell'illegalità a causa della decisione presa. Comunque, modalità basate sul nostro ordinamento giuridico di stampo liberale, come ad esempio l'assistenza ai malati in fin di vita da parte di non professionisti, devono continuare ad essere permesse anche con la nuova regolamentazione. In futuro è necessario evitare per quanto possibile inchieste penali con accertamenti di medicina legale.</p><p>Infine, anche la Confederazione non può vedere di buon occhio che in ogni cantone esistano condizioni legali differenti concernenti le organizzazioni di questo tipo, dando luogo nel peggiore dei casi ad un \"turismo intercantonale del suicidio\".</p>"
    },
    {
      "type": {
        "id": 5,
        "name": "Testo depositato"
      },
      "value": "<p>Ai sensi dell'articolo 160 capoverso 1 della Costituzione federale e dell'articolo 107 della legge sul Parlamento, inoltro l'iniziativa parlamentare seguente:</p><p>In base all'articolo 7 della Costituzione (dignità umana) e all'articolo 10 della Costituzione (diritto alla vita e alla libertà personale), deve essere formulata una legge in cui viene disciplinata l'eutanasia indiretta attiva e passiva e vengono previste condizioni per la sorveglianza delle organizzazioni che assistono chi decide di suicidarsi.</p>"
    },
    {
      "type": {
        "id": 1,
        "name": "Titolo dell'oggetto"
      },
      "value": "Disciplinare l'eutanasia in una legge"
    }
  ],
  "title": "Disciplinare l'eutanasia in una legge"
}