{
  "id": 20154110,
  "updated": "2019-02-18T19:03:06Z",
  "additionalIndexing": "32;34;44",
  "affairType": {
    "abbreviation": "Mo.",
    "id": 5,
    "name": "Mozione"
  },
  "author": {
    "councillor": {
      "code": 3036,
      "gender": "f",
      "id": 4134,
      "name": "Munz Martina",
      "officialDenomination": "Munz"
    },
    "faction": {
      "abbreviation": "Gruppo S",
      "id": 2,
      "name": "Gruppo socialista"
    },
    "type": "author"
  },
  "deposit": {
    "council": {
      "abbreviation": "CN",
      "id": 1,
      "name": "Consiglio nazionale",
      "type": "N"
    },
    "date": "2015-12-08T00:00:00Z",
    "legislativePeriod": 50,
    "session": "5001"
  },
  "descriptors": [

  ],
  "drafts": [
    {
      "consultation": {
        "resolutions": [
          {
            "category": {
              "id": 5,
              "name": "Amm."
            },
            "council": {
              "abbreviation": "CN",
              "id": 1,
              "name": "Consiglio nazionale",
              "type": "N"
            },
            "date": "2017-12-15T00:00:00Z",
            "text": "Tolto dal ruolo poiché la trattazione nella Camera non si è conclusa entro due anni",
            "type": 32
          }
        ]
      },
      "federalCouncilProposal": {
        "code": "-",
        "date": "2016-02-17T00:00:00Z",
        "text": "Il Consiglio federale propone di respingere la mozione."
      },
      "index": 0,
      "links": [

      ],
      "preConsultations": [

      ],
      "references": [

      ],
      "relatedDepartments": [
        {
          "abbreviation": "DEFR",
          "id": 8,
          "name": "Dipartimento dell'economia, della formazione e della ricerca",
          "leading": true
        }
      ],
      "states": [
        {
          "date": "/Date(1449529200000+0100)/",
          "id": 24,
          "name": "Non ancora trattato dalla Camera"
        },
        {
          "date": "/Date(1513292400000+0100)/",
          "id": 27,
          "name": "Liquidato"
        }
      ],
      "texts": [

      ]
    }
  ],
  "handling": {
    "date": "2017-12-15T00:00:00Z",
    "legislativePeriod": 50,
    "session": "5011"
  },
  "language": "it",
  "priorityCouncils": [
    {
      "abbreviation": "CN",
      "id": 1,
      "name": "Consiglio nazionale",
      "type": "N",
      "priority": 1
    }
  ],
  "relatedAffairs": [

  ],
  "roles": [
    {
      "councillor": {
        "code": 2632,
        "gender": "m",
        "id": 1120,
        "name": "Sommaruga Carlo",
        "officialDenomination": "Sommaruga Carlo"
      },
      "type": "cosign"
    },
    {
      "councillor": {
        "code": 2669,
        "gender": "m",
        "id": 3865,
        "name": "Steiert Jean-François",
        "officialDenomination": "Steiert"
      },
      "type": "cosign"
    },
    {
      "councillor": {
        "code": 2743,
        "gender": "f",
        "id": 4030,
        "name": "Birrer-Heimo Prisca",
        "officialDenomination": "Birrer-Heimo"
      },
      "type": "cosign"
    },
    {
      "councillor": {
        "code": 2666,
        "gender": "f",
        "id": 3830,
        "name": "Carobbio Guscetti Marina",
        "officialDenomination": "Carobbio Guscetti"
      },
      "type": "cosign"
    },
    {
      "councillor": {
        "code": 2745,
        "gender": "m",
        "id": 4032,
        "name": "Jans Beat",
        "officialDenomination": "Jans"
      },
      "type": "cosign"
    },
    {
      "councillor": {
        "code": 2608,
        "gender": "f",
        "id": 1147,
        "name": "Kiener Nellen Margret",
        "officialDenomination": "Kiener Nellen"
      },
      "type": "cosign"
    },
    {
      "councillor": {
        "code": 2417,
        "gender": "f",
        "id": 354,
        "name": "Semadeni Silva",
        "officialDenomination": "Semadeni"
      },
      "type": "cosign"
    },
    {
      "councillor": {
        "code": 2738,
        "gender": "m",
        "id": 4018,
        "name": "Maire Jacques-André",
        "officialDenomination": "Maire Jacques-André"
      },
      "type": "cosign"
    },
    {
      "councillor": {
        "code": 2569,
        "gender": "f",
        "id": 806,
        "name": "Graf Maya",
        "officialDenomination": "Graf Maya"
      },
      "type": "cosign"
    },
    {
      "councillor": {
        "code": 2630,
        "gender": "f",
        "id": 1129,
        "name": "Schenker Silvia",
        "officialDenomination": "Schenker Silvia"
      },
      "type": "cosign"
    },
    {
      "councillor": {
        "code": 2760,
        "gender": "m",
        "id": 4049,
        "name": "Aebischer Matthias",
        "officialDenomination": "Aebischer Matthias"
      },
      "type": "cosign"
    },
    {
      "councillor": {
        "code": 2763,
        "gender": "m",
        "id": 4061,
        "name": "Hardegger Thomas",
        "officialDenomination": "Hardegger"
      },
      "type": "cosign"
    },
    {
      "councillor": {
        "code": 2759,
        "gender": "m",
        "id": 4057,
        "name": "Wermuth Cédric",
        "officialDenomination": "Wermuth"
      },
      "type": "cosign"
    },
    {
      "councillor": {
        "code": 2792,
        "gender": "m",
        "id": 4076,
        "name": "Hadorn Philipp",
        "officialDenomination": "Hadorn"
      },
      "type": "cosign"
    },
    {
      "councillor": {
        "code": 2778,
        "gender": "m",
        "id": 4074,
        "name": "Fridez Pierre-Alain",
        "officialDenomination": "Fridez"
      },
      "type": "cosign"
    },
    {
      "councillor": {
        "code": 2795,
        "gender": "m",
        "id": 4091,
        "name": "Reynard Mathias",
        "officialDenomination": "Reynard"
      },
      "type": "cosign"
    },
    {
      "councillor": {
        "code": 3018,
        "gender": "m",
        "id": 4106,
        "name": "Naef Martin",
        "officialDenomination": "Naef"
      },
      "type": "cosign"
    },
    {
      "councillor": {
        "code": 3017,
        "gender": "f",
        "id": 4101,
        "name": "Bulliard-Marbach Christine",
        "officialDenomination": "Bulliard"
      },
      "type": "cosign"
    },
    {
      "councillor": {
        "code": 3014,
        "gender": "f",
        "id": 4107,
        "name": "Amarelle Cesla",
        "officialDenomination": "Amarelle"
      },
      "type": "cosign"
    },
    {
      "councillor": {
        "code": 3009,
        "gender": "f",
        "id": 4109,
        "name": "Piller Carrard Valérie",
        "officialDenomination": "Piller Carrard"
      },
      "type": "cosign"
    },
    {
      "councillor": {
        "code": 3007,
        "gender": "m",
        "id": 4113,
        "name": "Tornare Manuel",
        "officialDenomination": "Tornare"
      },
      "type": "cosign"
    },
    {
      "councillor": {
        "code": 3026,
        "gender": "f",
        "id": 4121,
        "name": "Gysi Barbara",
        "officialDenomination": "Gysi Barbara"
      },
      "type": "cosign"
    },
    {
      "councillor": {
        "code": 3034,
        "gender": "f",
        "id": 4130,
        "name": "Masshardt Nadine",
        "officialDenomination": "Masshardt"
      },
      "type": "cosign"
    },
    {
      "councillor": {
        "code": 3035,
        "gender": "f",
        "id": 4131,
        "name": "Friedl Claudia",
        "officialDenomination": "Friedl Claudia"
      },
      "type": "cosign"
    },
    {
      "councillor": {
        "code": 2726,
        "gender": "f",
        "id": 3923,
        "name": "Marra Ada",
        "officialDenomination": "Marra"
      },
      "type": "cosign"
    },
    {
      "councillor": {
        "code": 2583,
        "gender": "f",
        "id": 1131,
        "name": "Allemann Evi",
        "officialDenomination": "Allemann"
      },
      "type": "cosign"
    },
    {
      "councillor": {
        "code": 3094,
        "gender": "f",
        "id": 4199,
        "name": "Seiler Graf Priska",
        "officialDenomination": "Seiler Graf"
      },
      "type": "cosign"
    },
    {
      "councillor": {
        "code": 3020,
        "gender": "m",
        "id": 4115,
        "name": "Schwaab Jean Christophe",
        "officialDenomination": "Schwaab"
      },
      "type": "cosign"
    },
    {
      "councillor": {
        "code": 3036,
        "gender": "f",
        "id": 4134,
        "name": "Munz Martina",
        "officialDenomination": "Munz"
      },
      "faction": {
        "abbreviation": "Gruppo S",
        "id": 2,
        "name": "Gruppo socialista"
      },
      "type": "author"
    }
  ],
  "shortId": "15.4110",
  "state": {
    "id": 27,
    "name": "Liquidato",
    "doneKey": "1",
    "newKey": 0
  },
  "texts": [
    {
      "type": {
        "id": 6,
        "name": "Motivazione"
      },
      "value": "<p>L'economia denuncia la carenza di specialisti in informatica e recluta di continuo specialisti stranieri. In Svizzera ci sono sempre più informatici disoccupati. Nel cantone di Zurigo il loro numero si è duplicato dal 2008 al 2014, raggiungendo le 900 unità. La maggior parte ha più di 45 anni. Nel contempo aumenta rapidamente anche il numero degli informatici stranieri. Sono persone che hanno il permesso di soggiorno B e provengono da Paesi non UE/AELS o che possiedono un permesso di breve durata. </p><p>Nell'ambito dell'iniziativa sul personale qualificato vengono compiuti sforzi particolari per formare un maggior numero di nuove leve. Gli specialisti più anziani che rischiano di perdere il lavoro, invece, non vengono protetti dal pericolo di cadere in disoccupazione.</p><p>Lo studio IWSB (2015) sull'idoneità al mercato del lavoro degli informatici disoccupati \"over 45\" (Zürich/Bern: Amt für Wirtschaft und Arbeit des Kantons Zürich/ICTswitzerland) spiega che in sede di preselezione dei candidati a un posto vengono applicati appositi filtri di reclutamento (per quanto concerne, ad esempio, le capacità o i certificati assolutamente indispensabili), per cui i candidati più anziani vengono spesso esclusi automaticamente.</p><p>Occorre garantire una formazione continua sistematica, mirata e orientata alla prassi lungo l'arco di un'intera carriera. È soltanto così che gli informatici più anziani possono stare al passo con le esigenze e qualifiche necessarie negli ambienti economici e conseguire i certificati richiesti. Mediante programmi di formazione continua e riqualificazione bisogna aiutare gli informatici disoccupati a reinserirsi nel mondo del lavoro. </p><p>Mediante un marchio di qualità, ICTswitzerland è disposta a sostenere i programmi di formazione continua sistematici per collaboratori IT. Dapprima è però necessaria un'iniziativa di formazione. Con un solo marchio di qualità non si risolve il problema.</p>"
    },
    {
      "type": {
        "id": 14,
        "name": "Risposta del CF / Ufficio"
      },
      "value": "<p>La formazione e la formazione continua sono due aspetti molto importanti per l'idoneità al mercato del lavoro di tutte le persone professionalmente attive. A seconda del tipo di formazione, la Confederazione è competente sul piano della gestione, dello sviluppo e del coordinamento. Nel campo della formazione continua, invece, essa riveste insieme ai cantoni un ruolo sussidiario, intervenendo soltanto laddove si tratta di salvaguardare interessi specifici. Con la nuova legge sulla formazione continua (LFCo, FF 2014 4503) la Confederazione perfeziona le condizioni quadro per quel tipo di formazione continua prevalentemente organizzata da operatori privati. Concepire e sviluppare piani di formazione continua non è compito della Confederazione. Spetta invece agli operatori della formazione continua definire contenuti e realizzare piani strategici.</p><p>Nell'ambito dell'iniziativa sul personale qualificato la Confederazione esaminerà - insieme a cantoni, parti sociali, associazioni settoriali e di categoria - come formare o riconvertire professionalmente un maggior numero di specialisti indigeni del settore informatico. Anche il finanziamento delle formazione continua per lavoratori più avanti con gli anni (45più) sarà esaminato in modo approfondito.</p><p>Lo studio (IWSB, 2015, Arbeitsmarktfähigkeit arbeitsloser Informatiker 45plus; Zurigo/Berna: Amt für Wirtschaft und Arbeit des Kantons Zürich/ICTswitzerland) citato dall'autrice della mozione evidenzia che gli informatici \"over 45\" sono tutto sommato ben qualificati. Più spesso dei loro colleghi che hanno un'occupazione, tuttavia, essi non hanno conseguito un titolo formale. Gli esami federali di professione e degli esami professionali superiori, ad esempio, sono due strumenti creati dalla Confederazione che possono portare al conseguimento di un titolo formale, a prescindere dall'età dei candidati. La preparazione individuale, inoltre, tiene conto delle competenze già acquisite. I titoli formali, infine, hanno il vantaggio di offrire un ampio bagaglio di conoscenze di base e - contrariamente a molte offerte di formazione continua - di non essere improntati su prodotti specifici.</p><p>Vista la ripartizione delle competenze nel campo della formazione continua e le misure già intraprese, il Consiglio federale ritiene che la mozione non sia idonea a produrre i frutti sperati.</p>"
    },
    {
      "type": {
        "id": 5,
        "name": "Testo depositato"
      },
      "value": "<p>Il Consiglio federale è incaricato di sviluppare insieme agli ambienti economici un piano di formazione continua per specialisti in informatica. Questo piano deve consentire agli interessati di stare al passo con le esigenze dell'economia, riducendo così il loro rischio di finire in disoccupazione. Nel contempo, gli informatici disoccupati d'età un po' più avanzata devono essere reinseriti nel mondo del lavoro attraverso misure di formazione continua adeguate.</p>"
    },
    {
      "type": {
        "id": 1,
        "name": "Titolo dell'oggetto"
      },
      "value": "Proteggere dalla disoccupazione gli specialisti in informatica attraverso misure di formazione continua"
    }
  ],
  "title": "Proteggere dalla disoccupazione gli specialisti in informatica attraverso misure di formazione continua"
}